README.rst
setup.py
pyxtcp/__init__.py
pyxtcp.egg-info/PKG-INFO
pyxtcp.egg-info/SOURCES.txt
pyxtcp.egg-info/dependency_links.txt
pyxtcp.egg-info/not-zip-safe
pyxtcp.egg-info/requires.txt
pyxtcp.egg-info/top_level.txt
pyxtcp/http/__init__.py
pyxtcp/http/client.py
pyxtcp/http/server.py
pyxtcp/http/service.py
pyxtcp/http/util.py
pyxtcp/tcp/__init__.py
pyxtcp/tcp/tornado/__init__.py
pyxtcp/tcp/tornado/multi_client.py
pyxtcp/tcp/tornado/r_simple_client.py
pyxtcp/tcp/tornado/server.py
pyxtcp/tcp/tornado/simple_client.py
pyxtcp/tcp/tornado/util.py