Metadata-Version: 1.0
Name: pyxtcp
Version: 1.1.5
Summary: Tcp-based communication protocol, RPC protocol
Home-page: https://github.com/nashuiliang/xtcp
Author: chuangwang
Author-email: nashuiliang@gmail.com
License: Apache License 2.0
Keywords: RPC TCP pyxtcp xtcp protocol
Platform: UNKNOWN
